palm/__init__.py
palm/cli.py
palm/code_generator.py
palm/environment.py
palm/palm_config.py
palm/plugin_manager.py
palm/requirements.txt
palm/utils.py
palm/plugins/__init__.py
palm/plugins/base.py
palm/plugins/core/__init__.py
palm/plugins/core/core_plugin.py
palm/plugins/core/create_files.py
palm/plugins/core/commands/__init__.py
palm/plugins/core/commands/cmd_build.py
palm/plugins/core/commands/cmd_init.py
palm/plugins/core/commands/cmd_plugin.py
palm/plugins/core/commands/cmd_scaffold.py
palm/plugins/core/commands/cmd_update.py
palm/plugins/core/templates/__init__.py
palm/plugins/core/templates/command/__init__.py
palm/plugins/core/templates/command/new_cmd.tpl.py
palm/plugins/core/templates/command/template-config.yaml
palm/plugins/core/templates/command_group/__init__.py
palm/plugins/core/templates/command_group/new_cmd_group.tpl.py
palm/plugins/core/templates/command_group/template-config.yaml
palm/plugins/repo/__init__.py
palm/plugins/repo/repo_plugin.py
palm/plugins/test_internal/__init__.py
palm/plugins/test_internal/test_internal_plugin.py
palm/plugins/test_internal/commands/__init__.py
palm/plugins/test_internal/commands/cmd_run.py
palmcli-2.0.1.dist-info/LICENSE
palmcli-2.0.1.dist-info/METADATA
palmcli-2.0.1.dist-info/WHEEL
palmcli-2.0.1.dist-info/entry_points.txt
palmcli-2.0.1.dist-info/top_level.txt
palmcli-2.0.1.dist-info/RECORD
