Metadata-Version: 2.1
Name: palmcli
Version: 2.0.1
Summary: Palm CLI
Home-page: https://github.com/palmetto/palm-cli
Author: Palmetto - Data & Analytics team
Author-email: data-analytics-team@palmetto.com
License: Apache License 2.0
Platform: UNKNOWN
Classifier: Development Status :: 4 - Beta
Classifier: License :: OSI Approved :: Apache Software License
License-File: LICENSE
Requires-Dist: pygit2 (<1.6,>=1.5)
Requires-Dist: pyyaml (<5.5,>=5.0)
Requires-Dist: click (<7.2,>=7.1)
Requires-Dist: jinja2 (==2.11.3)
